dcgpy/_encode.py
dcgpy/core.so
dcgpy/_version.py
dcgpy/_simplify.py
dcgpy/_visualize.py
dcgpy/test.py
dcgpy/__init__.py
dcgpy/.libs/libboost_serialization-a2bbf0df.so.1.70.0
dcgpy/.libs/libmpfr-a5f70da1.so.6.0.2
dcgpy/.libs/libcoinlapack-1d9b926d.so.1.6.0
dcgpy/.libs/libpagmo-01c44f91.so.1.0
dcgpy/.libs/libgfortran-2e0d59d6.so.5.0.0
dcgpy/.libs/libcoinmumps-2bf998af.so.1.6.1
dcgpy/.libs/libipopt-9e3b663f.so.1.10.13
dcgpy/.libs/libobake-f3271ff2.so.1.0
dcgpy/.libs/libgmp-c0146b93.so.10.3.2
dcgpy/.libs/libcoinblas-6361cbe7.so.1.4.7
dcgpy/.libs/libz-eb09ad1d.so.1.2.3
dcgpy/.libs/libquadmath-2d0c479f.so.0.0.0
dcgpy/.libs/libtbb-2264f684.so.2
dcgpy/.libs/libnlopt-e9f4c2d2.so.0.10.0
dcgpy/.libs/libboost_python27-9485fa8b.so.1.70.0
dcgpy/.libs/libmp++-796aafdd.so.3.0
dcgpy-1.4.1.dist-info/top_level.txt
dcgpy-1.4.1.dist-info/RECORD
dcgpy-1.4.1.dist-info/METADATA
dcgpy-1.4.1.dist-info/WHEEL
